ccl_git_gud-0.0.10.data/scripts/git-gud
git_gud/__init__.py
git_gud/cmd.py
git_gud/feature.py
git_gud/init.py
git_gud/main.py
git_gud/pipelines.py
git_gud/readme.py
git_gud/release.py
git_gud/utils.py
ccl_git_gud-0.0.10.dist-info/LICENSE
ccl_git_gud-0.0.10.dist-info/METADATA
ccl_git_gud-0.0.10.dist-info/WHEEL
ccl_git_gud-0.0.10.dist-info/top_level.txt
ccl_git_gud-0.0.10.dist-info/RECORD
