Metadata-Version: 2.1
Name: ccl-git-gud
Version: 0.0.10
Summary: Gitlab workflow command line automation.
Home-page: https://gitlab.com/ccl-consulting/kubees/gud
Author: CCL Consulting
Author-email: ggau@ccl-consulting.fr
License: UNKNOWN
Platform: UNKNOWN
Classifier: Programming Language :: Python :: 3
Classifier: License :: OSI Approved :: MIT License
Classifier: Operating System :: OS Independent
Requires-Dist: loguru
Requires-Dist: urllib3
Requires-Dist: python-gitlab
Requires-Dist: jinja2
